{
  "main": {
    "id": "4d21bacbdf329fb1",
    "type": "split",
    "children": [
      {
        "id": "b7624b30c24b187b",
        "type": "tabs",
        "children": [
          {
            "id": "cc339a4839aaa9d6",
            "type": "leaf",
            "state": {
              "type": "markdown",
              "state": {
                "file": "操作系统/xv6/xv6-riscv-book-Chinese/Chapter-3.md",
                "mode": "source",
                "source": false
              }
            }
          }
        ]
      }
    ],
    "direction": "vertical"
  },
  "left": {
    "id": "ebd0ae169d48cc5f",
    "type": "split",
    "children": [
      {
        "id": "ac638be20db4e06b",
        "type": "tabs",
        "children": [
          {
            "id": "ad651b062e9f83fa",
            "type": "leaf",
            "state": {
              "type": "search",
              "state": {
                "query": "",
                "matchingCase": false,
                "explainSearch": false,
                "collapseAll": false,
                "extraContext": false,
                "sortOrder": "alphabetical"
              }
            }
          },
          {
            "id": "d394b480d32da822",
            "type": "leaf",
            "state": {
              "type": "bookmarks",
              "state": {}
            }
          },
          {
            "id": "8e39effb7c798476",
            "type": "leaf",
            "state": {
              "type": "file-explorer",
              "state": {
                "sortOrder": "alphabetical"
              }
            }
          }
        ],
        "currentTab": 2
      }
    ],
    "direction": "horizontal",
    "width": 200,
    "collapsed": true
  },
  "right": {
    "id": "36d4aad796e04c1e",
    "type": "split",
    "children": [
      {
        "id": "2c1421625739e5da",
        "type": "tabs",
        "children": [
          {
            "id": "ee9aab81f7f82e1d",
            "type": "leaf",
            "state": {
              "type": "backlink",
              "state": {
                "file": "操作系统/xv6/xv6-riscv-book-Chinese/Chapter-3.md",
                "collapseAll": true,
                "extraContext": true,
                "sortOrder": "alphabetical",
                "showSearch": false,
                "searchQuery": "",
                "backlinkCollapsed": false,
                "unlinkedCollapsed": true
              }
            }
          },
          {
            "id": "9fec8d9f726af05a",
            "type": "leaf",
            "state": {
              "type": "outgoing-link",
              "state": {
                "file": "操作系统/xv6/xv6-riscv-book-Chinese/Chapter-3.md",
                "linksCollapsed": true,
                "unlinkedCollapsed": true
              }
            }
          },
          {
            "id": "4ceacfa0fc1d0102",
            "type": "leaf",
            "state": {
              "type": "tag",
              "state": {
                "sortOrder": "frequency",
                "useHierarchy": true
              }
            }
          },
          {
            "id": "90d947202b2994d7",
            "type": "leaf",
            "state": {
              "type": "outline",
              "state": {
                "file": "操作系统/xv6/xv6-riscv-book-Chinese/Chapter-3.md"
              }
            }
          },
          {
            "id": "de6d158eac405474",
            "type": "leaf",
            "state": {
              "type": "all-properties",
              "state": {
                "sortOrder": "frequency",
                "showSearch": false,
                "searchQuery": ""
              }
            }
          }
        ],
        "currentTab": 3
      }
    ],
    "direction": "horizontal",
    "width": 200
  },
  "left-ribbon": {
    "hiddenItems": {
      "switcher:Open quick switcher": false,
      "graph:Open graph view": false,
      "canvas:Create new canvas": false,
      "daily-notes:Open today's daily note": false,
      "templates:Insert template": false,
      "command-palette:Open command palette": false
    }
  },
  "active": "cc339a4839aaa9d6",
  "lastOpenFiles": [
    "我狠C/Effective Modern Cpp/1.DeducingTypes/item3.md",
    "我狠C/Effective Modern Cpp/1.DeducingTypes/item2.md",
    "我狠C/Effective Modern Cpp/1.DeducingTypes/item4.md",
    "我狠C/Effective Modern Cpp/1.DeducingTypes/Untitled.md",
    "我狠C/Effective Modern Cpp/1.DeducingTypes/item1.md",
    "我狠C/C++ 登神长阶/C++ Modern Template Metaprogramming.md",
    "Algorithm/Sort.md",
    "操作系统/xv6/xv6-riscv-book-Chinese/Chapter-3.md",
    "操作系统/xv6/xv6-riscv-book-Chinese/Chapter-4.md",
    "操作系统/xv6/xv6-riscv-book-Chinese/Chapter-5.md",
    "操作系统/xv6/xv6-riscv-book-Chinese/Chapter-6.md",
    "操作系统/xv6/xv6-riscv-book-Chinese/Chapter-7.md",
    "操作系统/xv6/xv6-riscv-book-Chinese/Chapter-8.md",
    "操作系统/xv6/xv6-riscv-book-Chinese/Chapter-2.md",
    "2024-05-10.md",
    "Algorithm/字符串/KMP.md",
    "操作系统/linux操作系统/Unix IO.md",
    "images/Pasted image 20240508171543.png",
    "我狠C/C++ 登神长阶/工具/Makefile.md",
    "操作系统/linux操作系统/文件系统/Untitled.md",
    "操作系统/linux操作系统/Unix IO",
    "我狠C/C语言机制.md",
    "操作系统/xv6/xv6-riscv-book-Chinese/Chapter-1.md",
    "脚本/shell/bash.md",
    "脚本/python/os模块.md",
    "脚本/ANSI Escape Code.md",
    "tools/git.md",
    "python/命令行参数解析.md",
    "python",
    "Algorithm/位运算/Untitled",
    "操作系统/xv6/xv6-riscv-book-Chinese/assets/Figure-3.2.jpg",
    "操作系统/xv6/xv6-riscv-book-Chinese/assets/Figure-3.3.jpg",
    "操作系统/xv6/xv6-riscv-book-Chinese/assets/Figure-6.2.png",
    "操作系统/xv6/xv6-riscv-book-Chinese/assets/Figure-8.3.png",
    "操作系统/xv6/xv6-riscv-book-Chinese/assets/Figure-8.2.png",
    "操作系统/xv6/xv6-riscv-book-Chinese/assets/Figure-6.3.png",
    "操作系统/xv6/xv6-riscv-book-Chinese/assets/Figure-6.1.png",
    "操作系统/xv6/xv6-riscv-book-Chinese/assets/Figure-3.4.jpg",
    "操作系统/xv6/xv6-riscv-book-Chinese/assets/Figure-2.3.png",
    "操作系统/Untitled",
    "ismism",
    "编译器/GDB",
    "操作系统/并发",
    "脚本/shell",
    "脚本/python",
    "脚本",
    "未命名.canvas",
    "未命名 1.canvas"
  ]
}